calc_demo/__init__.py
calc_demo/calc_demo.py
calc_demo-0.0.2.data/scripts/calc_demo
calc_demo-0.0.2.dist-info/METADATA
calc_demo-0.0.2.dist-info/RECORD
calc_demo-0.0.2.dist-info/WHEEL
calc_demo-0.0.2.dist-info/top_level.txt
test/__init__.py
test/test_div.py
test/test_sum.py
