Metadata-Version: 2.1
Name: calc-demo
Version: 0.0.2
Summary: A small calc example package
Home-page: https://github.com/waldirio/calc_demo
Author: Waldirio
Author-email: waldirio@gmail.com
License: UNKNOWN
Platform: UNKNOWN
Classifier: Programming Language :: Python :: 3
Classifier: License :: OSI Approved :: MIT License
Classifier: Operating System :: OS Independent
